django_x509/__init__.py
django_x509/admin.py
django_x509/apps.py
django_x509/models.py
django_x509/settings.py
django_x509/urls.py
django_x509/base/__init__.py
django_x509/base/admin.py
django_x509/base/models.py
django_x509/migrations/0001_initial.py
django_x509/migrations/0002_certificate.py
django_x509/migrations/0003_rename_organization_field.py
django_x509/migrations/0004_auto_20171207_1450.py
django_x509/migrations/0005_organizational_unit_name.py
django_x509/migrations/0006_passphrase_field.py
django_x509/migrations/0007_serial_number_max_length.py
django_x509/migrations/0008_common_name_max_length.py
django_x509/migrations/0009_alter_ca_digest_alter_ca_key_length_and_more.py
django_x509/migrations/__init__.py
django_x509/static/django-x509/css/admin.css
django_x509/static/django-x509/css/renew_confirmation.css
django_x509/static/django-x509/js/x509-admin.js
django_x509/templates/admin/django_x509/change_form.html
django_x509/templates/admin/django_x509/renew_confirmation.html
django_x509/tests/__init__.py
django_x509/tests/test_admin.py
django_x509/tests/test_ca.py
django_x509/tests/test_cert.py
django_x509-1.3.dist-info/licenses/LICENSE
django_x509-1.3.dist-info/METADATA
django_x509-1.3.dist-info/WHEEL
django_x509-1.3.dist-info/top_level.txt
django_x509-1.3.dist-info/RECORD
