Metadata-Version: 2.4
Name: django-x509
Version: 1.3
Summary: Reusable django app to generate and manage x509 certificates
Home-page: https://github.com/openwisp/django-x509
Download-URL: https://github.com/openwisp/django-x509/releases
Author: Federico Capoano
Author-email: f.capoano@cineca.it
License: BSD
Keywords: django,x509,pki,PEM,openwisp
Platform: Platform Indipendent
Classifier: Development Status :: 5 - Production/Stable
Classifier: Environment :: Web Environment
Classifier: Topic :: Internet :: WWW/HTTP
Classifier: Intended Audience :: Developers
Classifier: License :: OSI Approved :: BSD License
Classifier: Operating System :: OS Independent
Classifier: Framework :: Django
Classifier: Topic :: Security :: Cryptography
Classifier: Programming Language :: Python :: 3
License-File: LICENSE
Requires-Dist: django<=5.3.0,>=4.2.0
Requires-Dist: openwisp-utils~=1.2.0
Requires-Dist: jsonfield<4.0.0,>=3.1.0
Requires-Dist: cryptography~=46.0.3
Requires-Dist: pyOpenSSL~=25.3.0
Dynamic: author
Dynamic: author-email
Dynamic: classifier
Dynamic: description
Dynamic: download-url
Dynamic: home-page
Dynamic: keywords
Dynamic: license
Dynamic: license-file
Dynamic: platform
Dynamic: requires-dist
Dynamic: summary
